insidertrading/__about__.py
insidertrading/__init__.py
insidertrading/db.py
insidertrading/insidertrading.py
insidertrading/rss.py
insidertrading/stockhistory.py
insidertrading-0.0.9.dist-info/METADATA
insidertrading-0.0.9.dist-info/WHEEL
insidertrading-0.0.9.dist-info/entry_points.txt
insidertrading-0.0.9.dist-info/licenses/LICENSE.txt
insidertrading-0.0.9.dist-info/RECORD
